xnoapi/__init__.py
xnoapi/metrics/__init__.py
xnoapi/metrics/portfolio.py
xnoapi/metrics/single_asset.py
xnoapi/metrics/st.py
xnoapi/paper/__init__.py
xnoapi/paper/portfolio.py
xnoapi/paper/single_asset.py
xnoapi/vn/__init__.py
xnoapi/vn/data/__init__.py
xnoapi/vn/data/const.py
xnoapi/vn/data/core.py
xnoapi/vn/data/derivatives.py
xnoapi/vn/data/stocks.py
xnoapi/vn/data/utils.py
xnoapi/vn/metrics/__init__.py
xnoapi/vn/metrics/backtest.py
xnoapi/vn/metrics/metrics.py
xnoapi-0.1.28.dist-info/licenses/LICENSE
xnoapi-0.1.28.dist-info/METADATA
xnoapi-0.1.28.dist-info/WHEEL
xnoapi-0.1.28.dist-info/top_level.txt
xnoapi-0.1.28.dist-info/RECORD
